claude_vault_mcp/__init__.py
claude_vault_mcp/approval_server.py
claude_vault_mcp/file_parsers.py
claude_vault_mcp/migration_state.py
claude_vault_mcp/security.py
claude_vault_mcp/server.py
claude_vault_mcp/session.py
claude_vault_mcp/tokenization.py
claude_vault_mcp/vault_client.py
claude_vault_mcp/tools/__init__.py
claude_vault_mcp/tools/auth.py
claude_vault_mcp/tools/example.py
claude_vault_mcp/tools/inject.py
claude_vault_mcp/tools/read.py
claude_vault_mcp/tools/scan.py
claude_vault_mcp/tools/write.py
claude_vault_mcp-1.4.0.dist-info/METADATA
claude_vault_mcp-1.4.0.dist-info/WHEEL
claude_vault_mcp-1.4.0.dist-info/entry_points.txt
claude_vault_mcp-1.4.0.dist-info/RECORD
