Metadata-Version: 2.4
Name: claude-vault-mcp
Version: 1.4.0
Summary: MCP server for HashiCorp Vault secret management via claude-vault
Project-URL: Homepage, https://github.com/weber8thomas/claude-vault
Project-URL: Repository, https://github.com/weber8thomas/claude-vault
Project-URL: Documentation, https://github.com/weber8thomas/claude-vault#readme
Project-URL: Issues, https://github.com/weber8thomas/claude-vault/issues
Author-email: Thomas Weber <weber8thomas@users.noreply.github.com>
License: MIT
Keywords: ai,claude,mcp,secrets,security,vault,webauthn
Classifier: Development Status :: 4 - Beta
Classifier: Intended Audience :: Developers
Classifier: License :: OSI Approved :: MIT License
Classifier: Programming Language :: Python :: 3
Classifier: Programming Language :: Python :: 3.11
Classifier: Programming Language :: Python :: 3.12
Classifier: Topic :: Security
Classifier: Topic :: System :: Systems Administration
Requires-Python: >=3.11
Requires-Dist: fastapi>=0.104.0
Requires-Dist: mcp>=1.1.0
Requires-Dist: python-dotenv>=1.0.1
Requires-Dist: pyyaml>=6.0
Requires-Dist: requests>=2.32.3
Requires-Dist: uvicorn>=0.24.0
Requires-Dist: webauthn>=2.0.0
